{"componentChunkName":"component---gatsby-lite-template-ts","path":"/crypto-art-121","result":{"pageContext":{"sitePath":"/crypto-art-121","data":{"postPage":{"sourceFilePath":"D:/Projects/rick-love-master/code/blog-content/posts/2021-01-21-crypto-art-121/crypto-art-121.md","sourceFileContent":"---\r\ntitle: \"Crypto Art 121\"\r\ndate: \"2021-01-21\"\r\npath: \"/crypto-art-121\"\r\nauthor: \"Rick Love\"\r\nexcerpt: \"1/21/21 21:21:21\"\r\ntags: crypto, art, ehtereum, nft\r\n---\r\n\r\n\r\nNFTs are revitalizing the ability for artists to make income. It also allows a software engineer like me the chance to create procedurally generated art defined in code.\r\n\r\nCode is my medium of creation, so this is my chance to make something that shines.\r\n\r\nRecently, I noticed an interesting symmetric time that 1/21/21 21:21:21 would be occuring soon (this is using the month/date/year format, but that still counts).\r\n\r\nSo, in a rush I'll be publishing my first crypto art NFT - using the ERC721 standard NFT smart contract base.\r\n\r\nHowever, as a bonus the goal is to mine this exactly at the right second. Hopefully, the community will help and we will be able to capture this unique moment in our human timeline.\r\n\r\n[![Crypto Art 121](art-121.png)](/art)\r\n\r\n[View the live art as it ticks to 1/21/21 21:21:21.](/art)\r\n\r\n","title":"Crypto Art 121","headers":[{"key":"title","value":"Crypto Art 121"},{"key":"date","value":"2021-01-21"},{"key":"path","value":"/crypto-art-121"},{"key":"author","value":"Rick Love"},{"key":"excerpt","value":"1/21/21 21:21:21"},{"key":"tags","value":"crypto, art, ehtereum, nft"}],"body":"\r\n\r\n\r\nNFTs are revitalizing the ability for artists to make income. It also allows a software engineer like me the chance to create procedurally generated art defined in code.\r\n\r\nCode is my medium of creation, so this is my chance to make something that shines.\r\n\r\nRecently, I noticed an interesting symmetric time that 1/21/21 21:21:21 would be occuring soon (this is using the month/date/year format, but that still counts).\r\n\r\nSo, in a rush I'll be publishing my first crypto art NFT - using the ERC721 standard NFT smart contract base.\r\n\r\nHowever, as a bonus the goal is to mine this exactly at the right second. Hopefully, the community will help and we will be able to capture this unique moment in our human timeline.\r\n\r\n[![Crypto Art 121](/blog-content/posts/2021-01-21-crypto-art-121/art-121.png)](/art)\r\n\r\n[View the live art as it ticks to 1/21/21 21:21:21.](/art)\r\n\r\n","summary":"NFTs are revitalizing the ability for artists to make income. It also allows a software engineer like me the chance to create procedurally generated art defined in code.\r\n\r\nCode is my medium of creation, so this is my chance to make something that shines.\r\n\r\nRecently, I noticed an interesting symmetric time that 1/21/21 21:21:21 would be occuring soon (this is using the month/date/year format, but that still counts).\r\n\r\nSo, in a rush I'll be publishing my first crypto art NFT - using the ERC721 standard NFT smart contract base.\r\n\r\nHowever, as a bonus the goal is to mine this exactly at the right second. Hopefully, the community will help and we will be able to capture this unique moment in our human timeline.\r\n\r\n[![Crypto Art 121](/blog-content/posts/2021-01-21-crypto-art-121/art-121.png)](/art)\r\n\r\n[View the live art as it ticks to 1/21/21 21:21:21.](/art)\n\n...","excerpt":"1/21/21 21:21:21","tags":["crypto","art","ehtereum","nft"],"order":-1611187200000,"dateLabel":"2021-01-21","relatedPages":[{"postSitePath":"/crypto-art-121","title":"Crypto Art 121","tags":["crypto","art","ehtereum","nft"],"dateLabel":"2021-01-21","order":-1611187200000}]}}}},"staticQueryHashes":[]}